code_opener_cli/__init__.py
code_opener_cli/main.py
code_opener_cli/path_definitions.py
code_opener_cli/resources/settings.json
code_opener_cli/tests/conftest.py
code_opener_cli/tests/test_main.py
code_opener_cli/utils/__init__.py
code_opener_cli/utils/config.py
code_opener_cli/utils/helpers.py
code_opener_cli-1.0.1.dist-info/entry_points.txt
code_opener_cli-1.0.1.dist-info/LICENSE
code_opener_cli-1.0.1.dist-info/WHEEL
code_opener_cli-1.0.1.dist-info/METADATA
code_opener_cli-1.0.1.dist-info/RECORD
