Metadata-Version: 2.1
Name: code-opener-cli
Version: 1.0.1
Summary: The CLI to handle your projects and Editors smartly
Author: Shantanu Joshi
Author-email: shantanujoshi7030@gmail.com
Requires-Python: >=3.6,<4.0
Classifier: Programming Language :: Python :: 3
Classifier: Programming Language :: Python :: 3.6
Classifier: Programming Language :: Python :: 3.7
Classifier: Programming Language :: Python :: 3.8
Classifier: Programming Language :: Python :: 3.9
Requires-Dist: typer[all] (>=0.3.2,<0.4.0)
